Metadata-Version: 2.1
Name: django-softdelete
Version: 0.11.4
Summary: Soft delete support for Django ORM, with undelete.
Author-email: Steve Coursen <smcoursen@gmail.com>
Project-URL: Homepage, https://github.com/scoursen/django-softdelete
Classifier: Environment :: Web Environment
Classifier: Framework :: Django
Classifier: License :: OSI Approved :: BSD License
License-File: LICENSE
